pysos.py
pysos-1.3.0.data/scripts/pysos.py
pysos-1.3.0.dist-info/LICENSE
pysos-1.3.0.dist-info/METADATA
pysos-1.3.0.dist-info/WHEEL
pysos-1.3.0.dist-info/top_level.txt
pysos-1.3.0.dist-info/RECORD
