Metadata-Version: 2.1
Name: pysos
Version: 1.3.0
Summary: Simple Object Storage - Persistent dicts and lists for python.
Home-page: https://github.com/dagnelies/pysos
Author: Arnaud Dagnelies
Author-email: arnaud.dagnelies@gmail.com
License: MIT
Keywords: persistent persistence dict list file
Classifier: Intended Audience :: Developers
Classifier: License :: OSI Approved :: MIT License
Classifier: Operating System :: OS Independent
Classifier: Programming Language :: Python :: 3
Classifier: Topic :: Database
License-File: LICENSE
